[
  {
    "_id": "682d59c0a11426187732bc5f",
    "gameId": "682d579aa11426187732bc4d",
    "pageId": "682d5c82a11426187732bced",
    "solution":  [
    {
      "stepIndex": 0,
      "action": {
        "loop": "redloop",
        "actions": [
          {
            "stepIndex": 1,
            "action": "moveLeft"
          }
        ]
      }
    },
    {
      "stepIndex": 2,
      "action": "moveUp"
    }
  ],
    "metadata": {
      "difficulty": "easy",
      "hintTemplate": "Try going up {n} times before turning right"
    }
  },
  {
    "_id": "682d59c0a11426187732bc5f",
    "gameId": "682d579aa11426187732bc4d",
    "pageId": "682d75137f8c8a86b6629888",
    "solution": [
    {
      "stepIndex": 0,
      "action": {
        "loop": "redloop",
        "actions": [
          {
            "stepIndex": 1,
            "action": "moveLeft"
          }
        ]
      }
    },
    {
      "stepIndex": 2,
      "action": "moveUpLeft"
    },
    {
      "stepIndex": 3,
      "action": "moveLeft"
    }
  ], 
    "metadata": {
      "difficulty": "easy",
      "hintTemplate": "Try going up {n} times before turning right"
    }
  },
  {
    "_id": "682d59c0a11426187732bc5f",
    "gameId": "682d579aa11426187732bc4d",
    "pageId": "682d79117f8c8a86b6629aac",
    "solution": [
    {
      "stepIndex": 0,
      "action": "moveUpRight"
    },
    {
      "stepIndex": 1,
      "action": {
        "loop": "redloop",
        "actions": [
          {
            "stepIndex": 2,
            "action": "moveRight"
          }
        ]
      }
    },
    {
      "stepIndex": 3,
      "action": "moveUpRight"
    }
  ], 
    "metadata": {
      "difficulty": "easy",
      "hintTemplate": "Try going up {n} times before turning right"
    }
  },
  {
    "_id": "682d59c0a11426187732bc5f",
    "gameId": "682d579aa11426187732bc4d",
    "pageId": "682d7a5e7f8c8a86b6629b89",
    "solution": [
    {
      "stepIndex": 0,
      "action": "moveLeft"
    },
    {
      "stepIndex": 1,
      "action": {
        "loop": "redloop",
        "actions": [
          {
            "stepIndex": 2,
            "action": "moveUpLeft"
          }
        ]
      }
    },
    {
      "stepIndex": 3,
      "action": "moveLeft"
    }
  ], 
    "metadata": {
      "difficulty": "easy",
      "hintTemplate": "Try going up {n} times before turning right"
    }
  },
  {
    "_id": "682d59c0a11426187732bc5f",
    "gameId": "682d579aa11426187732bc4d",
    "pageId": "682d7c8f7f8c8a86b6629c22",
    "solution": [
    {
      "stepIndex": 0,
      "action": "moveLeft"
    },
    {
      "stepIndex": 1,
      "action": {
        "loop": "redloop",
        "actions": [
          {
            "stepIndex": 2,
            "action": "moveUpRight"
          }
        ]
      }
    },
    {
      "stepIndex": 3,
      "action": "moveUpRight"
    }
  ], 
    "metadata": {
      "difficulty": "easy",
      "hintTemplate": "Try going up {n} times before turning right"
    }
  },
  {
    "_id": "682d59c0a11426187732bc5f",
    "gameId": "682d579aa11426187732bc4d",
    "pageId": "682d7d7a7f8c8a86b6629ca0",
    "solution": [
    {
      "stepIndex": 0,
      "action": "moveUpRight"
    },
    {
      "stepIndex": 1,
      "action": "moveRight"
    },
    {
      "stepIndex": 2,
      "action": {
        "loop": "redloop",
        "actions": [
          {
            "stepIndex": 3,
            "action": "moveUpRight"
          }
        ]
      }
    },
    {
      "stepIndex": 4,
      "action": "moveRight"
    }
  ], 
    "metadata": {
      "difficulty": "easy",
      "hintTemplate": "Try going up {n} times before turning right"
    }
  },
  {
    "_id": "682d59c0a11426187732bc5f",
    "gameId": "682d579aa11426187732bc4d",
    "pageId": "682d7e577f8c8a86b6629ce9",
    "solution": [
    {
      "stepIndex": 0,
      "action": "moveUpLeft"
    },
    {
      "stepIndex": 1,
      "action": "moveLeft"
    },
    {
      "stepIndex": 2,
      "action": {
        "loop": "redloop",
        "actions": [
          {
            "stepIndex": 3,
            "action": "moveUpLeft"
          }
        ]
      }
    },
    {
      "stepIndex": 4,
      "action": "moveLeft"
    },
    {
      "stepIndex": 5,
      "action": "moveUpLeft"
    }
  ], 
    "metadata": {
      "difficulty": "easy",
      "hintTemplate": "Try going up {n} times before turning right"
    }
  },
  {
    "_id": "682d59c0a11426187732bc5f",
    "gameId": "682d579aa11426187732bc4d",
    "pageId": "682d7e577f8c8a86b6629ce7",
    "solution": [
    {
      "stepIndex": 0,
      "action": {
        "loop": "redloop",
        "actions": [
          {
            "stepIndex": 1,
            "action": "moveUpLeft"
          },
          {
            "stepIndex": 2,
            "action": "moveLeft"
          }
        ]
      }
    },
    {
      "stepIndex": 3,
      "action": "moveUpLeft"
    }
  ], 
    "metadata": {
      "difficulty": "easy",
      "hintTemplate": "Try going up {n} times before turning right"
    }
  },
  {
    "_id": "682d59c0a11426187732bc5f",
    "gameId": "682d579aa11426187732bc4d",
    "pageId": "682d7e577f8c8a86b6629ceb",
    "solution": [
    {
      "stepIndex": 0,
      "action": "moveUpRight"
    },
    {
      "stepIndex": 1,
      "action": "moveRight"
    },
    {
      "stepIndex": 2,
      "action": {
        "loop": "redloop",
        "actions": [
          {
            "stepIndex": 3,
            "action": "moveLeft"
          },
          {
            "stepIndex": 4,
            "action": "moveUpLeft"
          }
        ]
      }
    },
    {
      "stepIndex": 5,
      "action": "moveUpLeft"
    }
  ], 
    "metadata": {
      "difficulty": "easy",
      "hintTemplate": "Try going up {n} times before turning right"
    }
  },
  {
    "_id": "682d59c0a11426187732bc5f",
    "gameId": "682d579aa11426187732bc4d",
    "pageId": "682d80ef7f8c8a86b6629d70",
    "solution": [
    {
      "stepIndex": 0,
      "action": "moveLeft"
    },
    {
      "stepIndex": 1,
      "action": "moveUpLeft"
    },
    {
      "stepIndex": 2,
      "action": {
        "loop": "redloop",
        "actions": [
          {
            "stepIndex": 3,
            "action": "moveUpRight"
          },
          {
            "stepIndex": 4,
            "action": "moveRight"
          }
        ]
      }
    },
    {
      "stepIndex": 5,
      "action": "moveRight"
    }
  ], 
    "metadata": {
      "difficulty": "easy",
      "hintTemplate": "Try going up {n} times before turning right"
    }
  }
]